{
    "tickets": {
        "counts": {
            "full": {
                "badged_up_hour": {
                    "2016-08-03 21:00": 1,
                    "2016-08-04 17:00": 3,
                    "2016-08-04 18:00": 3,
                    "2016-08-05 07:00": 1,
                    "2016-08-05 08:00": 9,
                    "2016-08-05 09:00": 6,
                    "2016-08-05 10:00": 7,
                    "2016-08-05 11:00": 4,
                    "2016-08-05 12:00": 4,
                    "2016-08-05 13:00": 2,
                    "2016-08-05 14:00": 11,
                    "2016-08-05 15:00": 7,
                    "2016-08-05 16:00": 5,
                    "2016-08-05 17:00": 4,
                    "2016-08-05 18:00": 3,
                    "2016-08-05 19:00": 3,
                    "2016-08-05 20:00": 1,
                    "2016-08-06 08:00": 45,
                    "2016-08-06 09:00": 321,
                    "2016-08-06 10:00": 365,
                    "2016-08-06 11:00": 188,
                    "2016-08-06 12:00": 27,
                    "2016-08-06 13:00": 220,
                    "2016-08-06 14:00": 104,
                    "2016-08-06 15:00": 51,
                    "2016-08-06 16:00": 9,
                    "2016-08-06 18:00": 1,
                    "2016-08-06 19:00": 1,
                    "2016-08-06 20:00": 2,
                    "2016-08-06 21:00": 1,
                    "2016-08-07 08:00": 4,
                    "2016-08-07 09:00": 15,
                    "2016-08-07 10:00": 22,
                    "2016-08-07 11:00": 21,
                    "2016-08-07 12:00": 11,
                    "2016-08-07 13:00": 3,
                    "2016-08-07 14:00": 2,
                    "2016-08-07 15:00": 1,
                    "2016-08-07 17:00": 2,
                    "2016-08-07 18:00": 6,
                    "2016-08-07 22:00": 1
                },
                "checked_in_hour": {
                    "2016-08-03 20:00": 30,
                    "2016-08-03 21:00": 21,
                    "2016-08-04 17:00": 38,
                    "2016-08-04 18:00": 22,
                    "2016-08-04 19:00": 2,
                    "2016-08-05 07:00": 14,
                    "2016-08-05 08:00": 94,
                    "2016-08-05 09:00": 154,
                    "2016-08-05 10:00": 184,
                    "2016-08-05 11:00": 168,
                    "2016-08-05 12:00": 180,
                    "2016-08-05 13:00": 122,
                    "2016-08-05 14:00": 97,
                    "2016-08-05 15:00": 60,
                    "2016-08-05 16:00": 41,
                    "2016-08-05 17:00": 50,
                    "2016-08-05 18:00": 47,
                    "2016-08-05 19:00": 29,
                    "2016-08-05 20:00": 13,
                    "2016-08-05 21:00": 8,
                    "2016-08-05 22:00": 2,
                    "2016-08-06 08:00": 15,
                    "2016-08-06 09:00": 13,
                    "2016-08-06 10:00": 19,
                    "2016-08-06 11:00": 17,
                    "2016-08-06 12:00": 14,
                    "2016-08-06 13:00": 16,
                    "2016-08-06 14:00": 6,
                    "2016-08-06 15:00": 4,
                    "2016-08-06 16:00": 2,
                    "2016-08-06 17:00": 1,
                    "2016-08-06 18:00": 1,
                    "2016-08-06 19:00": 4,
                    "2016-08-06 20:00": 1,
                    "2016-08-06 21:00": 1,
                    "2016-08-06 23:00": 1,
                    "2016-08-07 11:00": 5,
                    "2016-08-07 15:00": 1
                }
            },
            "kid": {
                "badged_up_hour": {
                    "2016-08-05 08:00": 4,
                    "2016-08-05 09:00": 1,
                    "2016-08-05 10:00": 4,
                    "2016-08-05 11:00": 6,
                    "2016-08-05 12:00": 2,
                    "2016-08-05 13:00": 4,
                    "2016-08-05 14:00": 1,
                    "2016-08-05 15:00": 2,
                    "2016-08-05 17:00": 4,
                    "2016-08-05 18:00": 1,
                    "2016-08-05 19:00": 1,
                    "2016-08-06 08:00": 4,
                    "2016-08-06 09:00": 30,
                    "2016-08-06 10:00": 13,
                    "2016-08-06 11:00": 12,
                    "2016-08-06 12:00": 1,
                    "2016-08-06 13:00": 17,
                    "2016-08-06 14:00": 9,
                    "2016-08-06 15:00": 1,
                    "2016-08-07 08:00": 1,
                    "2016-08-07 09:00": 1,
                    "2016-08-07 10:00": 1,
                    "2016-08-07 18:00": 1
                },
                "checked_in_hour": {
                    "2016-08-03 20:00": 1,
                    "2016-08-05 07:00": 2,
                    "2016-08-05 08:00": 12,
                    "2016-08-05 09:00": 14,
                    "2016-08-05 10:00": 21,
                    "2016-08-05 11:00": 18,
                    "2016-08-05 12:00": 14,
                    "2016-08-05 13:00": 10,
                    "2016-08-05 14:00": 1,
                    "2016-08-05 15:00": 6,
                    "2016-08-05 16:00": 2,
                    "2016-08-05 17:00": 4,
                    "2016-08-05 18:00": 3,
                    "2016-08-05 19:00": 1,
                    "2016-08-06 08:00": 1,
                    "2016-08-06 09:00": 2,
                    "2016-08-06 11:00": 2,
                    "2016-08-06 12:00": 2,
                    "2016-08-06 13:00": 3,
                    "2016-08-06 15:00": 2
                }
            },
            "paid": {
                "checked_in": {
                    "true": 1618,
                    "null": 1122
                },
                "badged_up": {
                    "false": 114,
                    "true": 1504,
                    "null": 1122
                }
            },
            "unpaid": {
                "checked_in": {
                    "null": 419
                },
                "badged_up": {
                    "null": 419
                }
            }
        }
    }
}